{"title":"Leetcode第13题：罗马数字转整数","slug":"2019091301","date":"2019-09-13T12:19:23.000Z","updated":"2019-09-13T13:43:37.000Z","comments":true,"path":"api/articles/2019091301.json","excerpt":"题目罗马数字包含以下七种字符: I， V， X， L，C，D 和 M。字符-&gt;数值<br>I-&gt;1<br>V-&gt;5<br>X-&gt;10<br>L-&gt;50<br>C-&gt;100<br>D-&gt;500<br>M-&gt;1000例如， 罗马数字 2 写做 II ，即为两个并列的 1。12 写做 XII ，即为 X + II 。 27 写做  XXVII, 即为 XX + V + II 。通常情况下，罗马数字中小的数字在大的数字的右边。但也存在特例，例如 4 不写做 IIII，而是 IV。数字 1 在数字 5 的左边，所表示的数等于大数 5 减小数 1 得到的数值 4 。同样地，数字 9 表示为 IX。这个特殊的规则只适用于以下六种情况：I 可以放在 V (5) 和 X (10) 的左边，来表示 4 和 9。X 可以放在 L (50) 和 C (100) 的左边，来表示 40 和 90。 C 可以放在 D (500) 和 M (1000) 的左边，来表示 400 和 900。给定一个罗马数字，将其转换成整数。输入确保在 1 到 3999 的范围内。","covers":["https://ae01.alicdn.com/kf/H3c60433b208e410a8d47793305c0c95c2.png","https://ae01.alicdn.com/kf/H82862c9b593141dab177416a7d21dc51M.png","https://puui.qpic.cn/fans_admin/0/3_1680187318_1568380291616/0"],"content":"<h2 id=\"题目\"><a href=\"#题目\" class=\"headerlink\" title=\"题目\"></a>题目</h2><p>罗马数字包含以下七种字符: I， V， X， L，C，D 和 M。</p>\n<blockquote>\n<p>字符-&gt;数值<br>I-&gt;1<br>V-&gt;5<br>X-&gt;10<br>L-&gt;50<br>C-&gt;100<br>D-&gt;500<br>M-&gt;1000</p>\n</blockquote>\n<p>例如， 罗马数字 2 写做 II ，即为两个并列的 1。12 写做 XII ，即为 X + II 。 27 写做  XXVII, 即为 XX + V + II 。</p>\n<p>通常情况下，罗马数字中小的数字在大的数字的右边。但也存在特例，例如 4 不写做 IIII，而是 IV。数字 1 在数字 5 的左边，所表示的数等于大数 5 减小数 1 得到的数值 4 。同样地，数字 9 表示为 IX。这个特殊的规则只适用于以下六种情况：</p>\n<ul>\n<li>I 可以放在 V (5) 和 X (10) 的左边，来表示 4 和 9。</li>\n<li>X 可以放在 L (50) 和 C (100) 的左边，来表示 40 和 90。 </li>\n<li>C 可以放在 D (500) 和 M (1000) 的左边，来表示 400 和 900。</li>\n</ul>\n<p>给定一个罗马数字，将其转换成整数。输入确保在 1 到 3999 的范围内。</p>\n<a id=\"more\"></a>\n<h2 id=\"示例\"><a href=\"#示例\" class=\"headerlink\" title=\"示例\"></a>示例</h2><p>示例 1:</p>\n<blockquote>\n<p><strong>输入:</strong> “III”<br><strong>输出:</strong> 3</p>\n</blockquote>\n<p>示例 2:</p>\n<blockquote>\n<p><strong>输入:</strong> “IV”<br><strong>输出:</strong> 4</p>\n</blockquote>\n<p>示例 3:</p>\n<blockquote>\n<p><strong>输入:</strong> “IX”<br><strong>输出:</strong> 9</p>\n</blockquote>\n<p>示例 4:</p>\n<blockquote>\n<p><strong>输入:</strong> “LVIII”<br><strong>输出:</strong> 58<br><strong>解释:</strong> L = 50, V= 5, III = 3.</p>\n</blockquote>\n<p>示例 5:</p>\n<blockquote>\n<p><strong>输入:</strong> “MCMXCIV”<br><strong>输出:</strong> 1994<br><strong>解释:</strong> M = 1000, CM = 900, XC = 90, IV = 4.</p>\n</blockquote>\n<h2 id=\"代码\"><a href=\"#代码\" class=\"headerlink\" title=\"代码\"></a>代码</h2><figure class=\"highlight java\"><table><tr><td class=\"gutter\"><pre><span class=\"line\">1</span><br><span class=\"line\">2</span><br><span class=\"line\">3</span><br><span class=\"line\">4</span><br><span class=\"line\">5</span><br><span class=\"line\">6</span><br><span class=\"line\">7</span><br><span class=\"line\">8</span><br><span class=\"line\">9</span><br><span class=\"line\">10</span><br><span class=\"line\">11</span><br><span class=\"line\">12</span><br><span class=\"line\">13</span><br><span class=\"line\">14</span><br><span class=\"line\">15</span><br><span class=\"line\">16</span><br><span class=\"line\">17</span><br><span class=\"line\">18</span><br><span class=\"line\">19</span><br><span class=\"line\">20</span><br><span class=\"line\">21</span><br><span class=\"line\">22</span><br><span class=\"line\">23</span><br><span class=\"line\">24</span><br><span class=\"line\">25</span><br><span class=\"line\">26</span><br><span class=\"line\">27</span><br></pre></td><td class=\"code\"><pre><span class=\"line\"><span class=\"class\"><span class=\"keyword\">class</span> <span class=\"title\">Solution</span> </span>&#123;</span><br><span class=\"line\">    <span class=\"function\"><span class=\"keyword\">public</span> <span class=\"keyword\">int</span> <span class=\"title\">romanToInt</span><span class=\"params\">(String s)</span> </span>&#123;</span><br><span class=\"line\">        String flagStr=<span class=\"string\">&quot;MDCLXVI&quot;</span>;</span><br><span class=\"line\">        <span class=\"keyword\">int</span> num=<span class=\"number\">0</span>;</span><br><span class=\"line\">        <span class=\"keyword\">for</span>(<span class=\"keyword\">int</span> i=<span class=\"number\">0</span>;i&lt;s.length();i++)&#123;</span><br><span class=\"line\">            <span class=\"keyword\">int</span> tmp=flagStr.length()-flagStr.indexOf(s.charAt(i));</span><br><span class=\"line\">            <span class=\"keyword\">boolean</span> flag=<span class=\"keyword\">true</span>;</span><br><span class=\"line\">            <span class=\"keyword\">if</span>(i&lt;s.length()-<span class=\"number\">1</span>&amp;&amp;flagStr.length()-flagStr.indexOf(s.charAt(i+<span class=\"number\">1</span>))&gt;tmp)&#123;</span><br><span class=\"line\">                flag=<span class=\"keyword\">false</span>;</span><br><span class=\"line\">            &#125;</span><br><span class=\"line\">            <span class=\"keyword\">int</span> tmp2=(tmp-<span class=\"number\">1</span>)/<span class=\"number\">2</span>;</span><br><span class=\"line\">            <span class=\"keyword\">int</span> val=<span class=\"number\">1</span>;</span><br><span class=\"line\">            <span class=\"keyword\">for</span>(<span class=\"keyword\">int</span> j=<span class=\"number\">0</span>;j&lt;tmp2;j++)&#123;</span><br><span class=\"line\">                val*=<span class=\"number\">10</span>;</span><br><span class=\"line\">            &#125;</span><br><span class=\"line\">            <span class=\"keyword\">if</span>(tmp%<span class=\"number\">2</span>==<span class=\"number\">0</span>)&#123;</span><br><span class=\"line\">                val*=<span class=\"number\">5</span>;</span><br><span class=\"line\">            &#125;</span><br><span class=\"line\">            <span class=\"keyword\">if</span>(flag)&#123;</span><br><span class=\"line\">                num+=val;</span><br><span class=\"line\">            &#125;<span class=\"keyword\">else</span>&#123;</span><br><span class=\"line\">                num-=val;</span><br><span class=\"line\">            &#125;</span><br><span class=\"line\">        &#125;</span><br><span class=\"line\">        <span class=\"keyword\">return</span> num;</span><br><span class=\"line\">    &#125;</span><br><span class=\"line\">&#125;</span><br></pre></td></tr></table></figure>\n<h3 id=\"运行结果\"><a href=\"#运行结果\" class=\"headerlink\" title=\"运行结果\"></a>运行结果</h3><p><img src=\"https://ae01.alicdn.com/kf/H3c60433b208e410a8d47793305c0c95c2.png\"></p>\n<h2 id=\"总结\"><a href=\"#总结\" class=\"headerlink\" title=\"总结\"></a>总结</h2><p>第12题是将数字转为罗马数，而这一题是将罗马数转为数字。看起来只是反过来，但其实里面涉及到的实现方法是不可逆的（或许可能可逆，但是给我的第一感觉是不可逆的，我就按不可逆做了）。还是将符号位由大到小写成字符串，然后遍历提供的罗马数字字符串，然后根据该罗马字在符号位字符串中距离最后一位的位置，就可以得到该位带表的数字（比如M就代表1000，D就代表500）</p>\n<ol>\n<li>其中像D这样的代表5xxx的（10进制的中间位数），他们距离末尾的距离均为双数，所以只需判断单双，如为双数便在10进制的基础上乘以5即可。</li>\n<li>对于4和9这样的特殊数字我们可以理解为5-1,10-1，写作IV，可以看出正常情况下前一位距离末位符号位的距离肯定是越来越小的，而I比V离末位更近，所以只需将I的+1操作改为-1，即-1+5，亦等于4。</li>\n</ol>\n<p><img src=\"https://ae01.alicdn.com/kf/H82862c9b593141dab177416a7d21dc51M.png\"></p>\n<p>最后，今天是八月十五，祝愿在家团圆、漂泊在外的所有人——中秋快乐。<br><img src=\"https://puui.qpic.cn/fans_admin/0/3_1680187318_1568380291616/0\"></p>\n","more":"<h2 id=\"示例\"><a href=\"#示例\" class=\"headerlink\" title=\"示例\"></a>示例</h2><p>示例 1:</p>\n<blockquote>\n<p><strong>输入:</strong> “III”<br><strong>输出:</strong> 3</p>\n</blockquote>\n<p>示例 2:</p>\n<blockquote>\n<p><strong>输入:</strong> “IV”<br><strong>输出:</strong> 4</p>\n</blockquote>\n<p>示例 3:</p>\n<blockquote>\n<p><strong>输入:</strong> “IX”<br><strong>输出:</strong> 9</p>\n</blockquote>\n<p>示例 4:</p>\n<blockquote>\n<p><strong>输入:</strong> “LVIII”<br><strong>输出:</strong> 58<br><strong>解释:</strong> L = 50, V= 5, III = 3.</p>\n</blockquote>\n<p>示例 5:</p>\n<blockquote>\n<p><strong>输入:</strong> “MCMXCIV”<br><strong>输出:</strong> 1994<br><strong>解释:</strong> M = 1000, CM = 900, XC = 90, IV = 4.</p>\n</blockquote>\n<h2 id=\"代码\"><a href=\"#代码\" class=\"headerlink\" title=\"代码\"></a>代码</h2><figure class=\"highlight java\"><table><tr><td class=\"gutter\"><pre><span class=\"line\">1</span><br><span class=\"line\">2</span><br><span class=\"line\">3</span><br><span class=\"line\">4</span><br><span class=\"line\">5</span><br><span class=\"line\">6</span><br><span class=\"line\">7</span><br><span class=\"line\">8</span><br><span class=\"line\">9</span><br><span class=\"line\">10</span><br><span class=\"line\">11</span><br><span class=\"line\">12</span><br><span class=\"line\">13</span><br><span class=\"line\">14</span><br><span class=\"line\">15</span><br><span class=\"line\">16</span><br><span class=\"line\">17</span><br><span class=\"line\">18</span><br><span class=\"line\">19</span><br><span class=\"line\">20</span><br><span class=\"line\">21</span><br><span class=\"line\">22</span><br><span class=\"line\">23</span><br><span class=\"line\">24</span><br><span class=\"line\">25</span><br><span class=\"line\">26</span><br><span class=\"line\">27</span><br></pre></td><td class=\"code\"><pre><span class=\"line\"><span class=\"class\"><span class=\"keyword\">class</span> <span class=\"title\">Solution</span> </span>&#123;</span><br><span class=\"line\">    <span class=\"function\"><span class=\"keyword\">public</span> <span class=\"keyword\">int</span> <span class=\"title\">romanToInt</span><span class=\"params\">(String s)</span> </span>&#123;</span><br><span class=\"line\">        String flagStr=<span class=\"string\">&quot;MDCLXVI&quot;</span>;</span><br><span class=\"line\">        <span class=\"keyword\">int</span> num=<span class=\"number\">0</span>;</span><br><span class=\"line\">        <span class=\"keyword\">for</span>(<span class=\"keyword\">int</span> i=<span class=\"number\">0</span>;i&lt;s.length();i++)&#123;</span><br><span class=\"line\">            <span class=\"keyword\">int</span> tmp=flagStr.length()-flagStr.indexOf(s.charAt(i));</span><br><span class=\"line\">            <span class=\"keyword\">boolean</span> flag=<span class=\"keyword\">true</span>;</span><br><span class=\"line\">            <span class=\"keyword\">if</span>(i&lt;s.length()-<span class=\"number\">1</span>&amp;&amp;flagStr.length()-flagStr.indexOf(s.charAt(i+<span class=\"number\">1</span>))&gt;tmp)&#123;</span><br><span class=\"line\">                flag=<span class=\"keyword\">false</span>;</span><br><span class=\"line\">            &#125;</span><br><span class=\"line\">            <span class=\"keyword\">int</span> tmp2=(tmp-<span class=\"number\">1</span>)/<span class=\"number\">2</span>;</span><br><span class=\"line\">            <span class=\"keyword\">int</span> val=<span class=\"number\">1</span>;</span><br><span class=\"line\">            <span class=\"keyword\">for</span>(<span class=\"keyword\">int</span> j=<span class=\"number\">0</span>;j&lt;tmp2;j++)&#123;</span><br><span class=\"line\">                val*=<span class=\"number\">10</span>;</span><br><span class=\"line\">            &#125;</span><br><span class=\"line\">            <span class=\"keyword\">if</span>(tmp%<span class=\"number\">2</span>==<span class=\"number\">0</span>)&#123;</span><br><span class=\"line\">                val*=<span class=\"number\">5</span>;</span><br><span class=\"line\">            &#125;</span><br><span class=\"line\">            <span class=\"keyword\">if</span>(flag)&#123;</span><br><span class=\"line\">                num+=val;</span><br><span class=\"line\">            &#125;<span class=\"keyword\">else</span>&#123;</span><br><span class=\"line\">                num-=val;</span><br><span class=\"line\">            &#125;</span><br><span class=\"line\">        &#125;</span><br><span class=\"line\">        <span class=\"keyword\">return</span> num;</span><br><span class=\"line\">    &#125;</span><br><span class=\"line\">&#125;</span><br></pre></td></tr></table></figure>\n<h3 id=\"运行结果\"><a href=\"#运行结果\" class=\"headerlink\" title=\"运行结果\"></a>运行结果</h3><p><img src=\"https://ae01.alicdn.com/kf/H3c60433b208e410a8d47793305c0c95c2.png\"></p>\n<h2 id=\"总结\"><a href=\"#总结\" class=\"headerlink\" title=\"总结\"></a>总结</h2><p>第12题是将数字转为罗马数，而这一题是将罗马数转为数字。看起来只是反过来，但其实里面涉及到的实现方法是不可逆的（或许可能可逆，但是给我的第一感觉是不可逆的，我就按不可逆做了）。还是将符号位由大到小写成字符串，然后遍历提供的罗马数字字符串，然后根据该罗马字在符号位字符串中距离最后一位的位置，就可以得到该位带表的数字（比如M就代表1000，D就代表500）</p>\n<ol>\n<li>其中像D这样的代表5xxx的（10进制的中间位数），他们距离末尾的距离均为双数，所以只需判断单双，如为双数便在10进制的基础上乘以5即可。</li>\n<li>对于4和9这样的特殊数字我们可以理解为5-1,10-1，写作IV，可以看出正常情况下前一位距离末位符号位的距离肯定是越来越小的，而I比V离末位更近，所以只需将I的+1操作改为-1，即-1+5，亦等于4。</li>\n</ol>\n<p><img src=\"https://ae01.alicdn.com/kf/H82862c9b593141dab177416a7d21dc51M.png\"></p>\n<p>最后，今天是八月十五，祝愿在家团圆、漂泊在外的所有人——中秋快乐。<br><img src=\"https://puui.qpic.cn/fans_admin/0/3_1680187318_1568380291616/0\"></p>","categories":[{"name":"开发","path":"api/categories/开发.json"}],"tags":[{"name":"JAVA","path":"api/tags/JAVA.json"},{"name":"算法","path":"api/tags/算法.json"}]}